MANIFEST.in
README.md
setup.py
bin/luna-ml
luna_ml/__init__.py
luna_ml.egg-info/PKG-INFO
luna_ml.egg-info/SOURCES.txt
luna_ml.egg-info/dependency_links.txt
luna_ml.egg-info/requires.txt
luna_ml.egg-info/top_level.txt
luna_ml/api/__init__.py
luna_ml/api/model_yaml.py
luna_ml/api/project_yaml.py
luna_ml/api/score_file.py
luna_ml/cli/__init__.py
luna_ml/cli/luna_cli.py
luna_ml/repository/__init__.py
luna_ml/repository/repo_reader.py
luna_ml/storage/__init__.py
luna_ml/storage/storage_localfs.py
luna_ml/task/__init__.py
luna_ml/task/executor.py
luna_ml/task/kube_apply.py
luna_ml/task/task.py
luna_ml/task/template/task-k8s-pod.yaml
luna_ml/tests/__init__.py
luna_ml/tests/test_executor.py
luna_ml/tests/test_repository.py