Metadata-Version: 2.1
Name: luna-ml
Version: 0.2.6
Summary: Luna ML client
Home-page: https://github.com/luna-ml/luna-ml
Author: Staroid
Author-email: moon@staroid.com
License: Apache License 2.0
Platform: UNKNOWN
Classifier: Development Status :: 3 - Alpha
Classifier: Intended Audience :: Developers
Classifier: Programming Language :: Python :: 3.6
Classifier: Programming Language :: Python :: 3.7
Classifier: Programming Language :: Python :: 3.8
Classifier: License :: OSI Approved :: Apache Software License
Classifier: Operating System :: OS Independent
Requires-Python: >=3.6
